yastyleguide/__init__.py
yastyleguide/checkers/__init__.py
yastyleguide/checkers/base.py
yastyleguide/checkers/complexity_line.py
yastyleguide/checkers/complexity_module.py
yastyleguide/checkers/loop.py
yastyleguide/options.py
yastyleguide/plugin.py
yastyleguide/types.py
yastyleguide/visitors/__init__.py
yastyleguide/visitors/complexity/__init__.py
yastyleguide/visitors/complexity/node_name.py
yastyleguide/visitors/complexity/stop_node.py
yastyleguide/visitors/complexity/use_node.py
yastyleguide/visitors/complexity/visitor.py
yastyleguide/visitors/loop.py
yastyleguide-0.2.0.dist-info/LICENSE
yastyleguide-0.2.0.dist-info/METADATA
yastyleguide-0.2.0.dist-info/WHEEL
yastyleguide-0.2.0.dist-info/entry_points.txt
yastyleguide-0.2.0.dist-info/RECORD
